[{"__type__":"cc.SpriteFrame","content":{"name":"tjj","texture":"acIFbS8EhJI6FKuZvPemkG","rect":[15,93,192,87],"offset":[-19,-6.5],"originalSize":[260,260],"capInsets":[0,0,0,0]}},[{"__type__":"cc.Prefab","_name":"tj","data":{"__id__":1}},{"__type__":"cc.Node","_name":"tj","_level":1,"_components":[{"__type__":"cc.Sprite","node":{"__id__":1},"_materials":[{"__uuid__":"ecpdLyjvZBwrvm+cedCcQy"}],"_spriteFrame":{"__uuid__":"0bjdxAEI9EeoIQisFrgTUG"},"_sizeMode":0}],"_prefab":{"__type__":"cc.PrefabInfo","root":{"__id__":1},"asset":{"__uuid__":"1ewZRtQ7lJlJWkI04b97ey"},"fileId":"41B1FlsVxCBai89vpcE4bK"},"_contentSize":{"__type__":"cc.Size","width":192,"height":87},"_position":{"__type__":"cc.Vec3","x":9.428,"y":273.399}}]]